smqtk_classifier/__init__.py
smqtk_classifier/_defaults.py
smqtk_classifier/classification_element_factory.py
smqtk_classifier/classify_descriptor_collection.py
smqtk_classifier/exceptions.py
smqtk_classifier/impls/__init__.py
smqtk_classifier/impls/classification_element/__init__.py
smqtk_classifier/impls/classification_element/file.py
smqtk_classifier/impls/classification_element/memory.py
smqtk_classifier/impls/classification_element/postgres.py
smqtk_classifier/impls/classify_descriptor/__init__.py
smqtk_classifier/impls/classify_descriptor/classify_index_label_descriptor.py
smqtk_classifier/impls/classify_descriptor_supervised/__init__.py
smqtk_classifier/impls/classify_descriptor_supervised/libsvm.py
smqtk_classifier/impls/classify_descriptor_supervised/sklearn_logistic_regression.py
smqtk_classifier/impls/classify_descriptor_supervised/sklearn_svm.py
smqtk_classifier/interfaces/__init__.py
smqtk_classifier/interfaces/classification_element.py
smqtk_classifier/interfaces/classify_descriptor.py
smqtk_classifier/interfaces/classify_descriptor_supervised.py
smqtk_classifier/interfaces/classify_image.py
smqtk_classifier/interfaces/classify_image_supervised.py
smqtk_classifier/py.typed
smqtk_classifier-0.20.0.dist-info/LICENSE.txt
smqtk_classifier-0.20.0.dist-info/METADATA
smqtk_classifier-0.20.0.dist-info/WHEEL
smqtk_classifier-0.20.0.dist-info/entry_points.txt
smqtk_classifier-0.20.0.dist-info/RECORD
